sanic_auth/__init__.py
Sanic_Auth-0.3.0.dist-info/AUTHORS
Sanic_Auth-0.3.0.dist-info/LICENSE
Sanic_Auth-0.3.0.dist-info/METADATA
Sanic_Auth-0.3.0.dist-info/WHEEL
Sanic_Auth-0.3.0.dist-info/top_level.txt
Sanic_Auth-0.3.0.dist-info/RECORD
