Metadata-Version: 2.1
Name: Sanic-Auth
Version: 0.3.0
Summary: Sanic-Auth - Simple Authentication for Sanic
Home-page: https://github.com/pyx/sanic-auth/
Author: Philip Xu and contributors
Author-email: pyx@xrefactor.com
License: BSD-New
Platform: any
Classifier: Development Status :: 4 - Beta
Classifier: Environment :: Web Environment
Classifier: Intended Audience :: Developers
Classifier: License :: OSI Approved :: BSD License
Classifier: Operating System :: OS Independent
Classifier: Programming Language :: Python :: 3.6
Classifier: Programming Language :: Python :: 3.7
Classifier: Programming Language :: Python :: 3.8
Classifier: Programming Language :: Python :: 3.9
Classifier: Topic :: Internet :: WWW/HTTP :: Dynamic Content
Classifier: Topic :: Software Development :: Libraries :: Python Modules
Provides-Extra: dev
